swiml_python_xml/__about__.py
swiml_python_xml/__init__.py
swiml_python_xml-2.3.1.dist-info/METADATA
swiml_python_xml-2.3.1.dist-info/WHEEL
swiml_python_xml-2.3.1.dist-info/licenses/LICENSE.txt
swiml_python_xml-2.3.1.dist-info/RECORD
