Metadata-Version: 2.4
Name: swiml_python_xml
Version: 2.3.1
Summary: Use Python to write Swimming Markup Language (swiML)
Project-URL: Documentation, https://github.com/bartneck/swiML#readme
Project-URL: Issues, https://github.com/bartneck/swiML/issues
Project-URL: Source, https://github.com/bartneck/swiML
Author-email: Christoph Bartneck <christoph.bartneck@canterbury.ac.nz>, Callum Lockhart <clo78@uclive.ac.nz>
License-Expression: MIT
License-File: LICENSE.txt
Classifier: License :: OSI Approved :: MIT License
Classifier: Operating System :: OS Independent
Classifier: Programming Language :: Python :: 3
Requires-Python: >=3.8
